envyaml/__init__.py
envyaml/envyaml.py
envyaml-1.10.211231.dist-info/LICENSE
envyaml-1.10.211231.dist-info/METADATA
envyaml-1.10.211231.dist-info/WHEEL
envyaml-1.10.211231.dist-info/top_level.txt
envyaml-1.10.211231.dist-info/RECORD
