Metadata-Version: 2.1
Name: envyaml
Version: 1.10.211231
Summary: Simple YAML configuration file parser with easy access for structured data
Home-page: https://github.com/thesimj/envyaml
Author: Mykola Bubelich
Author-email: m+github@bubelich.com
License: MIT
Platform: any
Classifier: Operating System :: OS Independent
Classifier: License :: OSI Approved :: MIT License
Classifier: Topic :: Utilities
Classifier: Intended Audience :: Developers
Classifier: Topic :: Software Development :: Libraries :: Python Modules
Classifier: Programming Language :: Python :: 2.7
Classifier: Programming Language :: Python :: 3.6
Classifier: Programming Language :: Python :: 3.7
Classifier: Programming Language :: Python :: 3.8
Classifier: Programming Language :: Python :: 3.9
Classifier: Programming Language :: Python :: 3.10
Requires-Python: >=2.7
License-File: LICENSE
